{
	"configurations" : 
	[
		{
			"directories" : 
			[
				{
					"build" : ".",
					"jsonFile" : "directory-.-Debug-f5ebdc15457944623624.json",
					"minimumCMakeVersion" : 
					{
						"string" : "3.21"
					},
					"projectIndex" : 0,
					"source" : ".",
					"targetIndexes" : 
					[
						0
					]
				}
			],
			"name" : "Debug",
			"projects" : 
			[
				{
					"directoryIndexes" : 
					[
						0
					],
					"name" : "wyklad2cpp",
					"targetIndexes" : 
					[
						0
					]
				}
			],
			"targets" : 
			[
				{
					"directoryIndex" : 0,
					"id" : "wyklad2cpp::@6890427a1f51a3e7e1df",
					"jsonFile" : "target-wyklad2cpp-Debug-dc8d13a1f7fd0c3d8a7c.json",
					"name" : "wyklad2cpp",
					"projectIndex" : 0
				}
			]
		}
	],
	"kind" : "codemodel",
	"paths" : 
	{
		"build" : "/home/piotrk/Pulpit/CPP/wyklad2/wyklad2cpp/cmake-build-debug",
		"source" : "/home/piotrk/Pulpit/CPP/wyklad2/wyklad2cpp"
	},
	"version" : 
	{
		"major" : 2,
		"minor" : 3
	}
}
